{
  "v": "5.7.4",
  "fr": 30,
  "ip": 0,
  "op": 60,
  "w": 200,
  "h": 200,
  "nm": "train",
  "ddd": 0,
  "assets": [],
  "layers": [
    {
      "ddd": 0,
      "ind": 1,
      "ty": 4,
      "nm": "Train Body",
      "sr": 1,
      "ks": {
        "o": { "a": 0, "k": 100 },
        "r": { "a": 0, "k": 0 },
        "p": { "a": 0, "k": [100, 100, 0] },
        "a": { "a": 0, "k": [0, 0, 0] },
        "s": { "a": 0, "k": [100, 100, 100] }
      },
      "shapes": [
        {
          "ty": "rc",
          "d": 1,
          "s": { "a": 0, "k": [120, 60] },
          "p": { "a": 0, "k": [0, 0] },
          "r": { "a": 0, "k": 20 },
          "nm": "Train Body",
          "hd": false
        },
        {
          "ty": "el",
          "p": { "a": 0, "k": [-40, 30] },
          "s": { "a": 0, "k": [20, 20] },
          "nm": "Wheel 1",
          "hd": false
        },
        {
          "ty": "el",
          "p": { "a": 0, "k": [40, 30] },
          "s": { "a": 0, "k": [20, 20] },
          "nm": "Wheel 2",
          "hd": false
        }
      ],
      "ao": 0,
      "ip": 0,
      "op": 60,
      "st": 0,
      "bm": 0
    },
    {
      "ddd": 0,
      "ind": 2,
      "ty": 4,
      "nm": "Smoke",
      "sr": 1,
      "ks": {
        "o": { "a": 0, "k": 100 },
        "r": { "a": 0, "k": 0 },
        "p": { "a": 1, "k": [
          { "i": { "x": 0.667, "y": 1 }, "o": { "x": 0.333, "y": 0 }, "t": 0, "s": [0, -40, 0] },
          { "t": 60, "s": [0, -80, 0] }
        ] },
        "a": { "a": 0, "k": [0, 0, 0] },
        "s": { "a": 0, "k": [100, 100, 100] }
      },
      "shapes": [
        {
          "ty": "el",
          "p": { "a": 0, "k": [0, 0] },
          "s": { "a": 0, "k": [30, 30] },
          "nm": "Smoke Puff",
          "hd": false
        }
      ],
      "ao": 0,
      "ip": 0,
      "op": 60,
      "st": 0,
      "bm": 0
    }
  ],
  "markers": []
} 